fileshelf/__init__.py
fileshelf/__init__.pyc
fileshelf-0.0.1.dist-info/DESCRIPTION.rst
fileshelf-0.0.1.dist-info/METADATA
fileshelf-0.0.1.dist-info/RECORD
fileshelf-0.0.1.dist-info/WHEEL
fileshelf-0.0.1.dist-info/metadata.json
fileshelf-0.0.1.dist-info/top_level.txt
