Metadata-Version: 2.0
Name: fileshelf
Version: 0.0.1
Summary: Organize and Search your Files.
Home-page: https://github.com/MacHu-GWU/
Author: Sanhe Hu
Author-email: husanhe@gmail.com
License: MIT
Download-URL: https://github.com/MacHu-GWU//tarball/2017-11-04
Platform: Windows
Platform: MacOS
Platform: Unix
Classifier: Development Status :: 4 - Beta
Classifier: Intended Audience :: Developers
Classifier: License :: OSI Approved :: MIT License
Classifier: Natural Language :: English
Classifier: Operating System :: Microsoft :: Windows
Classifier: Operating System :: MacOS
Classifier: Operating System :: Unix
Classifier: Programming Language :: Python
Classifier: Programming Language :: Python :: 2.7
Classifier: Programming Language :: Python :: 3.4
Classifier: Programming Language :: Python :: 3.5
Classifier: Programming Language :: Python :: 3.6
